pandas_rs9/__init__.py
pandas_rs9/module.py
pandas_rs9-0.1.dist-info/METADATA
pandas_rs9-0.1.dist-info/WHEEL
pandas_rs9-0.1.dist-info/top_level.txt
pandas_rs9-0.1.dist-info/RECORD
